framext_swastikgorai/__init__.py
framext_swastikgorai/framext.py
framext-0.0.1.dist-info/LICENCE
framext-0.0.1.dist-info/METADATA
framext-0.0.1.dist-info/WHEEL
framext-0.0.1.dist-info/top_level.txt
framext-0.0.1.dist-info/RECORD
