Metadata-Version: 2.1
Name: framext
Version: 0.0.1
Summary: A python package to extract frames from a video
Author-email: Swastik Gorai <swastigoraitemp@gmail.com>
Project-URL: Homepage, https://github.com/SwastikGorai/FrameExtVideo
Project-URL: Bug Tracker, https://github.com/SwastikGorai/FrameExtVideo/issues
Classifier: Programming Language :: Python :: 3
Classifier: License :: OSI Approved :: MIT License
Classifier: Operating System :: OS Independent
Requires-Python: >=3.9
License-File: LICENCE
